binding_configuration.py
usb_device.py
usbip_server.py
usbipd.py
usbipd-0.0.7.dist-info/licenses/LICENSE
usbipd-0.0.7.dist-info/METADATA
usbipd-0.0.7.dist-info/WHEEL
usbipd-0.0.7.dist-info/entry_points.txt
usbipd-0.0.7.dist-info/top_level.txt
usbipd-0.0.7.dist-info/RECORD
