Metadata-Version: 2.4
Name: usbipd
Version: 0.0.7
Summary: A Python USB/IP server for sharing USB devices over the network
Author-email: Alexander Brinkman <abrinkman@gmail.com>
License: GPL-3.0
Project-URL: Homepage, https://github.com/abrinkman/usbipd-python
Project-URL: Repository, https://github.com/abrinkman/usbipd-python.git
Project-URL: Issues, https://github.com/abrinkman/usbipd-python/issues
Keywords: usb,usbip,network,device-sharing
Classifier: Programming Language :: Python :: 3
Classifier: Programming Language :: Python :: 3.11
Classifier: Programming Language :: Python :: 3.12
Classifier: License :: OSI Approved :: GNU General Public License v3 (GPLv3)
Classifier: Operating System :: MacOS
Classifier: Operating System :: Microsoft :: Windows
Classifier: Operating System :: POSIX :: Linux
Classifier: Topic :: System :: Networking
Classifier: Development Status :: 3 - Alpha
Classifier: Intended Audience :: Developers
Classifier: Intended Audience :: System Administrators
Requires-Python: >=3.11
License-File: LICENSE
Requires-Dist: pyusb>=1.2.1
Requires-Dist: libusb>=1.0.29
Provides-Extra: dev
Requires-Dist: pip-tools>=7.0.0; extra == "dev"
Requires-Dist: ruff>=0.14.0; extra == "dev"
Requires-Dist: mypy>=1.0.0; extra == "dev"
Requires-Dist: reuse>=6.2.0; extra == "dev"
Dynamic: license-file
